digicubes_flask/__init__.py
digicubes_flask/exceptions.py
digicubes_flask/structures.py
digicubes_flask/version.json
digicubes_flask/cfg/__init__.py
digicubes_flask/cfg/default_configuration.yaml
digicubes_flask/cfg/logging.yaml
digicubes_flask/client/__init__.py
digicubes_flask/client/cache/__init__.py
digicubes_flask/client/cache/cache.py
digicubes_flask/client/cache/redis_cache.py
digicubes_flask/client/proxy/__init__.py
digicubes_flask/client/proxy/abstract_proxy.py
digicubes_flask/client/proxy/right_proxy.py
digicubes_flask/client/proxy/role_proxy.py
digicubes_flask/client/proxy/school_proxy.py
digicubes_flask/client/proxy/user_proxy.py
digicubes_flask/client/service/__init__.py
digicubes_flask/client/service/abstract_service.py
digicubes_flask/client/service/filter.py
digicubes_flask/client/service/right_service.py
digicubes_flask/client/service/role_service.py
digicubes_flask/client/service/school_service.py
digicubes_flask/client/service/user_service.py
digicubes_flask/email/__init__.py
digicubes_flask/email/automailer.py
digicubes_flask/email/templates/user_verification_html.jinja
digicubes_flask/email/templates/user_verification_plain.jinja
digicubes_flask/web/__init__.py
digicubes_flask/web/account_manager.py
digicubes_flask/web/commandline.py
digicubes_flask/web/wtforms_widgets.py
digicubes_flask/web/modules/__init__.py
digicubes_flask/web/modules/account/__init__.py
digicubes_flask/web/modules/account/blueprint.py
digicubes_flask/web/modules/account/forms.py
digicubes_flask/web/modules/admin/__init__.py
digicubes_flask/web/modules/admin/blueprint.py
digicubes_flask/web/modules/admin/forms.py
digicubes_flask/web/modules/admin/rfc.py
digicubes_flask/web/modules/admin/routes/__init__.py
digicubes_flask/web/modules/admin/routes/school.py
digicubes_flask/web/modules/blockly/__init__.py
digicubes_flask/web/modules/blockly/blueprint.py
digicubes_flask/web/modules/headmaster/__init__.py
digicubes_flask/web/modules/headmaster/blueprint.py
digicubes_flask-0.0.33.dist-info/LICENSE
digicubes_flask-0.0.33.dist-info/METADATA
digicubes_flask-0.0.33.dist-info/WHEEL
digicubes_flask-0.0.33.dist-info/top_level.txt
digicubes_flask-0.0.33.dist-info/RECORD
