Metadata-Version: 2.1
Name: digicubes-flask
Version: 0.0.33
Summary: A digicubes flask addon
Home-page: UNKNOWN
Author: Klaas Nebuhr, Marion Nebuhr
Author-email: klaas.nebuhr@gmail.com
License: Apache License Version 2.0
Keywords: flask digicubes api learning platform
Platform: UNKNOWN
Classifier: License :: OSI Approved :: Apache Software License
Classifier: Development Status :: 3 - Alpha
Classifier: Intended Audience :: Developers
Classifier: Programming Language :: Python :: 3
Classifier: Programming Language :: Python :: 3.6
Classifier: Programming Language :: Python :: 3.7
Classifier: Framework :: AsyncIO
Classifier: Topic :: Software Development :: Libraries :: Python Modules
Classifier: Operating System :: OS Independent
Requires-Dist: attrs (==20.1.0)
Requires-Dist: babel (==2.8.0)
Requires-Dist: cattrs (==1.0.0)
Requires-Dist: certifi (==2020.6.20)
Requires-Dist: chardet (==3.0.4)
Requires-Dist: click (==7.1.2)
Requires-Dist: dnspython (==2.0.0)
Requires-Dist: email-validator (==1.1.1)
Requires-Dist: flask-babel (==1.0.0)
Requires-Dist: flask-wtf (==0.14.3)
Requires-Dist: flask (==1.1.2)
Requires-Dist: gunicorn (==20.0.4)
Requires-Dist: idna (==2.10)
Requires-Dist: itsdangerous (==1.1.0)
Requires-Dist: jinja2 (==2.11.2)
Requires-Dist: libgravatar (==0.2.4)
Requires-Dist: markdown (==3.2.2)
Requires-Dist: markupsafe (==1.1.1)
Requires-Dist: pyaml (==20.4.0)
Requires-Dist: pyjwt (==1.7.1)
Requires-Dist: python-dotenv (==0.14.0)
Requires-Dist: pytz (==2020.1)
Requires-Dist: pyyaml (==5.3.1)
Requires-Dist: redis (==3.5.3)
Requires-Dist: requests (==2.24.0)
Requires-Dist: urllib3 (==1.25.10)
Requires-Dist: werkzeug (==1.0.1)
Requires-Dist: wtforms (==2.3.3)
